Metadata-Version: 2.4
Name: my-simple-package-jonas-jack
Version: 0.1.0
Summary: A simple example Python package with implemented content.
Author-email: jonas <dzdengzhu@gmail.com>
License: MIT License
Project-URL: Homepage, https://github.com/dengzhu-hub/my-awesome-package.git
Keywords: example,tutorial,package,simple
Classifier: Development Status :: 3 - Alpha
Classifier: Intended Audience :: Developers
Classifier: License :: OSI Approved :: MIT License
Classifier: Operating System :: OS Independent
Classifier: Programming Language :: Python :: 3
Classifier: Programming Language :: Python :: 3.7
Classifier: Programming Language :: Python :: 3.8
Classifier: Programming Language :: Python :: 3.9
Classifier: Programming Language :: Python :: 3.10
Classifier: Programming Language :: Python :: 3.11
Classifier: Programming Language :: Python :: 3.12
Classifier: Topic :: Software Development :: Libraries :: Python Modules
Classifier: Topic :: Utilities
Requires-Python: >=3.7
License-File: LICENSE
Dynamic: license-file
